desk/__init__.py
desk/abis/erc20.json
desk/abis/vault.json
desk/api.py
desk/auth.py
desk/constant/common.py
desk/constant/contract.py
desk/enum.py
desk/exchange.py
desk/info.py
desk/main.py
desk/py.typed
desk/types.py
desk/utils/__init__.py
desk/utils/contract.py
desk/utils/error.py
desk/utils/mapper.py
desk/utils/utils.py
desk/ws_manager.py
desk_python_sdk-1.1.2.dist-info/LICENSE
desk_python_sdk-1.1.2.dist-info/METADATA
desk_python_sdk-1.1.2.dist-info/WHEEL
desk_python_sdk-1.1.2.dist-info/entry_points.txt
desk_python_sdk-1.1.2.dist-info/RECORD
