Metadata-Version: 2.3
Name: desk-python-sdk
Version: 1.1.2
Summary: DESK Python SDK
License: MIT
Author: chenciao8
Author-email: chenciao8@gmail.com
Requires-Python: >=3.9,<4.0
Classifier: Development Status :: 4 - Beta
Classifier: License :: OSI Approved :: MIT License
Classifier: Programming Language :: Python :: 3
Classifier: Programming Language :: Python :: 3.9
Classifier: Programming Language :: Python :: 3.10
Classifier: Programming Language :: Python :: 3.11
Classifier: Programming Language :: Python :: 3.12
Classifier: Programming Language :: Python :: 3.13
Requires-Dist: eth-account (>=0.13.1,<0.14.0)
Requires-Dist: eth-keys (>=0.6.1,<0.7.0)
Requires-Dist: requests (>=2.32.3,<3.0.0)
Requires-Dist: web3 (>=7.0.0,<8.0.0)
Requires-Dist: websocket-client (>=1.8.0,<2.0.0)
Project-URL: Changelog, https://github.com/TradeOnDESK/desk-python-sdk/releases
Project-URL: Documentation, https://github.com/TradeOnDESK/desk-python-sdk
Project-URL: Homepage, https://github.com/TradeOnDESK/desk-python-sdk
Project-URL: Repository, https://github.com/TradeOnDESK/desk-python-sdk
